ddataflow/__init__.py
ddataflow/data_source.py
ddataflow/data_sources.py
ddataflow/ddataflow.py
ddataflow/downloader.py
ddataflow/exceptions.py
ddataflow/sampling/__init__.py
ddataflow/sampling/default.py
ddataflow/sampling/sampler.py
ddataflow/setup/__init__.py
ddataflow/setup/ddataflow_config.py
ddataflow/setup/setup_project.py
ddataflow/utils.py
ddataflow-1.1.16.dist-info/LICENSE.txt
ddataflow-1.1.16.dist-info/METADATA
ddataflow-1.1.16.dist-info/WHEEL
ddataflow-1.1.16.dist-info/entry_points.txt
ddataflow-1.1.16.dist-info/RECORD
