Metadata-Version: 2.1
Name: DDataFlow
Version: 1.1.16
Summary: A tool for end2end data tests
Home-page: https://github.com/getyourguide/DDataFlow
Author: Data products GYG
Author-email: engineering.data-products@getyourguide.com
Requires-Python: >=3.8,<4
Classifier: Programming Language :: Python :: 3
Classifier: Programming Language :: Python :: 3.8
Classifier: Programming Language :: Python :: 3.9
Classifier: Programming Language :: Python :: 3.10
Classifier: Programming Language :: Python :: 3.11
Classifier: Programming Language :: Python :: 3.12
Requires-Dist: databricks-cli (>=0.16)
Requires-Dist: fire (>=0.4)
Requires-Dist: oauthlib (>=3.2.1)
Requires-Dist: pyspark (>3)
Requires-Dist: urllib3 (>=1.24.2)
Project-URL: Repository, https://github.com/getyourguide/DDataFlow
